{"_id":"tiny-emitter","_rev":"37-67db44d919d4b742f686704ce8221805","name":"tiny-emitter","description":"A tiny (less than 1k) event emitter library","dist-tags":{"latest":"1.0.2"},"versions":{"0.1.0":{"name":"tiny-emitter","version":"0.1.0","description":"A tiny (less than 500 bytes) event emitter library","main":"index.js","scripts":{"test":"node test/index.js | node_modules/.bin/tspec"},"repository":{"type":"git","url":"https://github.com/scottcorgan/tiny-emitter.git"},"keywords":["event","emitter","pubsub","tiny","events","bind"],"author":{"name":"Scott Corgan"},"license":"MIT","bugs":{"url":"https://github.com/scottcorgan/tiny-emitter/issues"},"devDependencies":{"tape":"~2.3.2","tap-spec":"~0.1.1"},"_id":"tiny-emitter@0.1.0","dist":{"shasum":"b8f6a6e6b3363a4e31c619c92945019cb77a8f16","tarball":"https://registry.npmjs.org/tiny-emitter/-/tiny-emitter-0.1.0.tgz"},"_from":".","_npmVersion":"1.3.11","_npmUser":{"name":"scottcorgan","email":"scottcorgan@gmail.com"},"maintainers":[{"name":"scottcorgan","email":"scottcorgan@gmail.com"}],"directories":{}},"0.1.1":{"name":"tiny-emitter","version":"0.1.1","description":"A tiny (less than 500 bytes) event emitter library","main":"index.js","scripts":{"test":"node test/index.js | node_modules/.bin/tspec"},"repository":{"type":"git","url":"https://github.com/scottcorgan/tiny-emitter.git"},"keywords":["event","emitter","pubsub","tiny","events","bind"],"author":{"name":"Scott Corgan"},"license":"MIT","bugs":{"url":"https://github.com/scottcorgan/tiny-emitter/issues"},"devDependencies":{"tape":"~2.3.2","tap-spec":"~0.1.1"},"_id":"tiny-emitter@0.1.1","dist":{"shasum":"6789f05e85acabb64e27fc3151c2e6ee13838bfd","tarball":"https://registry.npmjs.org/tiny-emitter/-/tiny-emitter-0.1.1.tgz"},"_from":".","_npmVersion":"1.3.11","_npmUser":{"name":"scottcorgan","email":"scottcorgan@gmail.com"},"maintainers":[{"name":"scottcorgan","email":"scottcorgan@gmail.com"}],"directories":{}},"0.1.2":{"name":"tiny-emitter","version":"0.1.2","description":"A tiny (less than 500 bytes) event emitter library","main":"index.js","scripts":{"test":"node test/index.js | node_modules/.bin/tspec"},"repository":{"type":"git","url":"https://github.com/scottcorgan/tiny-emitter.git"},"keywords":["event","emitter","pubsub","tiny","events","bind"],"author":{"name":"Scott Corgan"},"license":"MIT","bugs":{"url":"https://github.com/scottcorgan/tiny-emitter/issues"},"devDependencies":{"tape":"~2.3.2","tap-spec":"~0.1.1"},"_id":"tiny-emitter@0.1.2","dist":{"shasum":"7adfab187bf4a0cda362c88d26290e3df906419c","tarball":"https://registry.npmjs.org/tiny-emitter/-/tiny-emitter-0.1.2.tgz"},"_from":".","_npmVersion":"1.3.11","_npmUser":{"name":"scottcorgan","email":"scottcorgan@gmail.com"},"maintainers":[{"name":"scottcorgan","email":"scottcorgan@gmail.com"}],"directories":{}},"0.1.3":{"name":"tiny-emitter","version":"0.1.3","description":"A tiny (less than 500 bytes) event emitter library","main":"index.js","scripts":{"test":"node test/index.js | node_modules/.bin/tspec"},"repository":{"type":"git","url":"https://github.com/scottcorgan/tiny-emitter.git"},"keywords":["event","emitter","pubsub","tiny","events","bind"],"author":{"name":"Scott Corgan"},"license":"MIT","bugs":{"url":"https://github.com/scottcorgan/tiny-emitter/issues"},"devDependencies":{"tape":"~2.3.2","tap-spec":"~0.1.1"},"_id":"tiny-emitter@0.1.3","dist":{"shasum":"08c97c33b87f82b3ff05715e98b18da6417f3019","tarball":"https://registry.npmjs.org/tiny-emitter/-/tiny-emitter-0.1.3.tgz"},"_from":".","_npmVersion":"1.3.11","_npmUser":{"name":"scottcorgan","email":"scottcorgan@gmail.com"},"maintainers":[{"name":"scottcorgan","email":"scottcorgan@gmail.com"}],"directories":{}},"0.1.4":{"name":"tiny-emitter","version":"0.1.4","description":"A tiny (less than 1k) event emitter library","main":"index.js","scripts":{"test":"node test/index.js | node_modules/.bin/tspec","bundle":"node_modules/.bin/browserify index.js > dist/tinyemitter.js -s TinyEmitter && echo 'Bundled'","minify":"node_modules/.bin/uglifyjs dist/tinyemitter.js -o dist/tinyemitter.min.js && echo 'Minified'","build":"npm test && npm run bundle && npm run minify"},"repository":{"type":"git","url":"https://github.com/scottcorgan/tiny-emitter.git"},"keywords":["event","emitter","pubsub","tiny","events","bind"],"author":{"name":"Scott Corgan"},"license":"MIT","bugs":{"url":"https://github.com/scottcorgan/tiny-emitter/issues"},"devDependencies":{"tape":"~2.3.2","tap-spec":"~0.1.1","browserify":"~3.18.0","uglify-js":"~2.4.8"},"_id":"tiny-emitter@0.1.4","dist":{"shasum":"75f04c4ce612dc5a5474acb16d0ce7019d12f039","tarball":"https://registry.npmjs.org/tiny-emitter/-/tiny-emitter-0.1.4.tgz"},"_from":".","_npmVersion":"1.3.11","_npmUser":{"name":"scottcorgan","email":"scottcorgan@gmail.com"},"maintainers":[{"name":"scottcorgan","email":"scottcorgan@gmail.com"}],"directories":{}},"0.1.5":{"name":"tiny-emitter","version":"0.1.5","description":"A tiny (less than 1k) event emitter library","main":"index.js","scripts":{"test":"node test/index.js | node_modules/.bin/tspec","bundle":"node_modules/.bin/browserify index.js > dist/tinyemitter.js -s TinyEmitter && echo 'Bundled'","minify":"node_modules/.bin/uglifyjs dist/tinyemitter.js -o dist/tinyemitter.min.js -m && echo 'Minified'","build":"npm test && npm run bundle && npm run minify","size":"node_modules/.bin/uglifyjs index.js -o minified.js -m && ls -l && rm minified.js"},"repository":{"type":"git","url":"https://github.com/scottcorgan/tiny-emitter.git"},"keywords":["event","emitter","pubsub","tiny","events","bind"],"author":{"name":"Scott Corgan"},"license":"MIT","bugs":{"url":"https://github.com/scottcorgan/tiny-emitter/issues"},"devDependencies":{"tape":"~2.3.2","tap-spec":"~0.1.1","browserify":"~3.18.0","uglify-js":"~2.4.8"},"_id":"tiny-emitter@0.1.5","dist":{"shasum":"650dedb3bd5604b31ee19528d11342903ce3bbdd","tarball":"https://registry.npmjs.org/tiny-emitter/-/tiny-emitter-0.1.5.tgz"},"_from":".","_npmVersion":"1.3.11","_npmUser":{"name":"scottcorgan","email":"scottcorgan@gmail.com"},"maintainers":[{"name":"scottcorgan","email":"scottcorgan@gmail.com"}],"directories":{}},"0.1.6":{"name":"tiny-emitter","version":"0.1.6","description":"A tiny (less than 1k) event emitter library","main":"index.js","scripts":{"test":"node_modules/.bin/testling | node_modules/.bin/tspec","bundle":"node_modules/.bin/browserify index.js > dist/tinyemitter.js -s TinyEmitter && echo 'Bundled'","minify":"node_modules/.bin/uglifyjs dist/tinyemitter.js -o dist/tinyemitter.min.js -m && echo 'Minified'","build":"npm test && npm run bundle && npm run minify","size":"node_modules/.bin/uglifyjs index.js -o minified.js -m && ls -l && rm minified.js"},"repository":{"type":"git","url":"https://github.com/scottcorgan/tiny-emitter.git"},"keywords":["event","emitter","pubsub","tiny","events","bind"],"author":{"name":"Scott Corgan"},"license":"MIT","bugs":{"url":"https://github.com/scottcorgan/tiny-emitter/issues"},"devDependencies":{"tape":"~2.3.2","tap-spec":"~0.1.3","browserify":"~3.18.0","uglify-js":"~2.4.8","testling":"~1.5.6"},"testling":{"files":["test/index.js"],"browsers":["iexplore/10.0","iexplore/9.0","firefox/16..latest","chrome/22..latest","safari/5.1..latest","ipad/6.0..latest","iphone/6.0..latest","android-browser/4.2..latest"]},"_id":"tiny-emitter@0.1.6","dist":{"shasum":"96b9374ec759e3ebc53f304084606e38491806da","tarball":"https://registry.npmjs.org/tiny-emitter/-/tiny-emitter-0.1.6.tgz"},"_from":".","_npmVersion":"1.3.11","_npmUser":{"name":"scottcorgan","email":"scottcorgan@gmail.com"},"maintainers":[{"name":"scottcorgan","email":"scottcorgan@gmail.com"}],"directories":{}},"0.1.7":{"name":"tiny-emitter","version":"0.1.7","description":"A tiny (less than 1k) event emitter library","main":"index.js","scripts":{"test":"node_modules/.bin/testling | node_modules/.bin/tspec","bundle":"node_modules/.bin/browserify index.js > dist/tinyemitter.js -s TinyEmitter && echo 'Bundled'","minify":"node_modules/.bin/uglifyjs dist/tinyemitter.js -o dist/tinyemitter.min.js -m && echo 'Minified'","build":"npm test && npm run bundle && npm run minify","size":"node_modules/.bin/uglifyjs index.js -o minified.js -m && ls -l && rm minified.js"},"repository":{"type":"git","url":"https://github.com/scottcorgan/tiny-emitter.git"},"keywords":["event","emitter","pubsub","tiny","events","bind"],"author":{"name":"Scott Corgan"},"license":"MIT","bugs":{"url":"https://github.com/scottcorgan/tiny-emitter/issues"},"devDependencies":{"tape":"~2.3.2","tap-spec":"~0.1.3","browserify":"~3.18.0","uglify-js":"~2.4.8","testling":"~1.5.6"},"testling":{"files":["test/index.js"],"browsers":["iexplore/10.0","iexplore/9.0","firefox/16..latest","chrome/22..latest","safari/5.1..latest","ipad/6.0..latest","iphone/6.0..latest","android-browser/4.2..latest"]},"_id":"tiny-emitter@0.1.7","dist":{"shasum":"78a00bee6e55a5faf6f4b639d19ddd87ea6bdc11","tarball":"https://registry.npmjs.org/tiny-emitter/-/tiny-emitter-0.1.7.tgz"},"_from":".","_npmVersion":"1.3.11","_npmUser":{"name":"scottcorgan","email":"scottcorgan@gmail.com"},"maintainers":[{"name":"scottcorgan","email":"scottcorgan@gmail.com"}],"directories":{}},"0.1.8":{"name":"tiny-emitter","version":"0.1.8","description":"A tiny (less than 1k) event emitter library","main":"index.js","scripts":{"test":"node_modules/.bin/testling | node_modules/.bin/tspec","bundle":"node_modules/.bin/browserify index.js > dist/tinyemitter.js -s TinyEmitter && echo 'Bundled'","minify":"node_modules/.bin/uglifyjs dist/tinyemitter.js -o dist/tinyemitter.min.js -m && echo 'Minified'","build":"npm test && npm run bundle && npm run minify","size":"node_modules/.bin/uglifyjs index.js -o minified.js -m && ls -l && rm minified.js"},"repository":{"type":"git","url":"https://github.com/scottcorgan/tiny-emitter.git"},"keywords":["event","emitter","pubsub","tiny","events","bind"],"author":{"name":"Scott Corgan"},"license":"MIT","bugs":{"url":"https://github.com/scottcorgan/tiny-emitter/issues"},"devDependencies":{"tape":"~2.3.2","tap-spec":"~0.1.3","browserify":"~3.18.0","uglify-js":"~2.4.8","testling":"~1.5.6"},"testling":{"files":["test/index.js"],"browsers":["iexplore/10.0","iexplore/9.0","firefox/16..latest","chrome/22..latest","safari/5.1..latest","ipad/6.0..latest","iphone/6.0..latest","android-browser/4.2..latest"]},"_id":"tiny-emitter@0.1.8","dist":{"shasum":"1aff4920502b3619717c1957cbe8d40e6e053dd1","tarball":"https://registry.npmjs.org/tiny-emitter/-/tiny-emitter-0.1.8.tgz"},"_from":".","_npmVersion":"1.3.11","_npmUser":{"name":"scottcorgan","email":"scottcorgan@gmail.com"},"maintainers":[{"name":"scottcorgan","email":"scottcorgan@gmail.com"}],"directories":{}},"0.1.9":{"name":"tiny-emitter","version":"0.1.9","description":"A tiny (less than 1k) event emitter library","main":"index.js","scripts":{"test":"node_modules/.bin/testling | node_modules/.bin/tspec","bundle":"node_modules/.bin/browserify index.js > dist/tinyemitter.js -s TinyEmitter && echo 'Bundled'","minify":"node_modules/.bin/uglifyjs dist/tinyemitter.js -o dist/tinyemitter.min.js -m && echo 'Minified'","build":"npm test && npm run bundle && npm run minify","size":"node_modules/.bin/uglifyjs index.js -o minified.js -m && ls -l && rm minified.js"},"repository":{"type":"git","url":"https://github.com/scottcorgan/tiny-emitter.git"},"keywords":["event","emitter","pubsub","tiny","events","bind"],"author":{"name":"Scott Corgan"},"license":"MIT","bugs":{"url":"https://github.com/scottcorgan/tiny-emitter/issues"},"devDependencies":{"tape":"~2.3.2","tap-spec":"~0.1.3","browserify":"~3.18.0","uglify-js":"~2.4.8","testling":"~1.5.6"},"testling":{"files":["test/index.js"],"browsers":["iexplore/10.0","iexplore/9.0","firefox/16..latest","chrome/22..latest","safari/5.1..latest","ipad/6.0..latest","iphone/6.0..latest","android-browser/4.2..latest"]},"_id":"tiny-emitter@0.1.9","dist":{"shasum":"404d85c2553142fc49e3fa4e25bc72506b3b5b79","tarball":"https://registry.npmjs.org/tiny-emitter/-/tiny-emitter-0.1.9.tgz"},"_from":".","_npmVersion":"1.3.11","_npmUser":{"name":"scottcorgan","email":"scottcorgan@gmail.com"},"maintainers":[{"name":"scottcorgan","email":"scottcorgan@gmail.com"}],"directories":{}},"0.1.10":{"name":"tiny-emitter","version":"0.1.10","description":"A tiny (less than 1k) event emitter library","main":"index.js","scripts":{"test":"node_modules/.bin/testling | node_modules/.bin/tspec","bundle":"node_modules/.bin/browserify index.js > dist/tinyemitter.js -s TinyEmitter && echo 'Bundled'","minify":"node_modules/.bin/uglifyjs dist/tinyemitter.js -o dist/tinyemitter.min.js -m && echo 'Minified'","build":"npm test && npm run bundle && npm run minify","size":"node_modules/.bin/uglifyjs index.js -o minified.js -m && ls -l && rm minified.js"},"repository":{"type":"git","url":"https://github.com/scottcorgan/tiny-emitter.git"},"keywords":["event","emitter","pubsub","tiny","events","bind"],"author":{"name":"Scott Corgan"},"license":"MIT","bugs":{"url":"https://github.com/scottcorgan/tiny-emitter/issues"},"devDependencies":{"tape":"~2.3.2","tap-spec":"~0.1.3","browserify":"~3.18.0","uglify-js":"~2.4.8","testling":"~1.5.6"},"testling":{"files":["test/index.js"],"browsers":["iexplore/10.0","iexplore/9.0","firefox/16..latest","chrome/22..latest","safari/5.1..latest","ipad/6.0..latest","iphone/6.0..latest","android-browser/4.2..latest"]},"_id":"tiny-emitter@0.1.10","dist":{"shasum":"c392291c268f1186b1776d1f2b469dcb97931e30","tarball":"https://registry.npmjs.org/tiny-emitter/-/tiny-emitter-0.1.10.tgz"},"_from":".","_npmVersion":"1.3.11","_npmUser":{"name":"scottcorgan","email":"scottcorgan@gmail.com"},"maintainers":[{"name":"scottcorgan","email":"scottcorgan@gmail.com"}],"directories":{}},"0.1.11":{"name":"tiny-emitter","version":"0.1.11","description":"A tiny (less than 1k) event emitter library","main":"index.js","scripts":{"test":"node_modules/.bin/testling | node_modules/.bin/tspec","bundle":"node_modules/.bin/browserify index.js > dist/tinyemitter.js -s TinyEmitter && echo 'Bundled'","minify":"node_modules/.bin/uglifyjs dist/tinyemitter.js -o dist/tinyemitter.min.js -m && echo 'Minified'","build":"npm test && npm run bundle && npm run minify","size":"node_modules/.bin/uglifyjs index.js -o minified.js -m && ls -l && rm minified.js"},"repository":{"type":"git","url":"https://github.com/scottcorgan/tiny-emitter.git"},"keywords":["event","emitter","pubsub","tiny","events","bind"],"author":{"name":"Scott Corgan"},"license":"MIT","bugs":{"url":"https://github.com/scottcorgan/tiny-emitter/issues"},"devDependencies":{"tape":"~2.3.2","tap-spec":"~0.1.3","browserify":"~3.18.0","uglify-js":"~2.4.8","testling":"~1.5.6"},"testling":{"files":["test/index.js"],"browsers":["iexplore/10.0","iexplore/9.0","firefox/16..latest","chrome/22..latest","safari/5.1..latest","ipad/6.0..latest","iphone/6.0..latest","android-browser/4.2..latest"]},"_id":"tiny-emitter@0.1.11","dist":{"shasum":"472232f06679b6f9b49c5fc4162a22471b0e546d","tarball":"https://registry.npmjs.org/tiny-emitter/-/tiny-emitter-0.1.11.tgz"},"_from":".","_npmVersion":"1.3.11","_npmUser":{"name":"scottcorgan","email":"scottcorgan@gmail.com"},"maintainers":[{"name":"scottcorgan","email":"scottcorgan@gmail.com"}],"directories":{}},"0.1.12":{"name":"tiny-emitter","version":"0.1.12","description":"A tiny (less than 1k) event emitter library","main":"index.js","scripts":{"test":"node_modules/.bin/testling | node_modules/.bin/tspec","bundle":"node_modules/.bin/browserify index.js > dist/tinyemitter.js -s TinyEmitter && echo 'Bundled'","minify":"node_modules/.bin/uglifyjs dist/tinyemitter.js -o dist/tinyemitter.min.js -m && echo 'Minified'","build":"npm test && npm run bundle && npm run minify","size":"node_modules/.bin/uglifyjs index.js -o minified.js -m && ls -l && rm minified.js"},"repository":{"type":"git","url":"https://github.com/scottcorgan/tiny-emitter.git"},"keywords":["event","emitter","pubsub","tiny","events","bind"],"author":{"name":"Scott Corgan"},"license":"MIT","bugs":{"url":"https://github.com/scottcorgan/tiny-emitter/issues"},"devDependencies":{"tape":"~2.3.2","tap-spec":"~0.1.3","browserify":"~3.18.0","uglify-js":"~2.4.8","testling":"~1.5.6"},"testling":{"files":["test/index.js"],"browsers":["iexplore/10.0","iexplore/9.0","firefox/16..latest","chrome/22..latest","safari/5.1..latest","ipad/6.0..latest","iphone/6.0..latest","android-browser/4.2..latest"]},"_id":"tiny-emitter@0.1.12","dist":{"shasum":"38500b9198925f08ca90523bf932282db6fd19f1","tarball":"https://registry.npmjs.org/tiny-emitter/-/tiny-emitter-0.1.12.tgz"},"_from":".","_npmVersion":"1.3.11","_npmUser":{"name":"scottcorgan","email":"scottcorgan@gmail.com"},"maintainers":[{"name":"scottcorgan","email":"scottcorgan@gmail.com"}],"directories":{}},"1.0.0":{"name":"tiny-emitter","version":"1.0.0","description":"A tiny (less than 1k) event emitter library","main":"index.js","scripts":{"test":"testling | node_modules/.bin/tspec","bundle":"browserify index.js > dist/tinyemitter.js -s TinyEmitter && echo 'Bundled'","minify":"uglifyjs dist/tinyemitter.js -o dist/tinyemitter.min.js -m && echo 'Minified'","build":"npm test && npm run bundle && npm run minify","size":"uglifyjs index.js -o minified.js -m && ls -l && rm minified.js"},"repository":{"type":"git","url":"https://github.com/scottcorgan/tiny-emitter.git"},"keywords":["event","emitter","pubsub","tiny","events","bind"],"author":{"name":"Scott Corgan"},"license":"MIT","bugs":{"url":"https://github.com/scottcorgan/tiny-emitter/issues"},"devDependencies":{"tape":"~2.3.2","tap-spec":"~0.1.3","browserify":"~3.18.0","uglify-js":"~2.4.8","testling":"~1.5.6"},"testling":{"files":["test/index.js"],"browsers":["iexplore/10.0","iexplore/9.0","firefox/16..latest","chrome/22..latest","safari/5.1..latest","ipad/6.0..latest","iphone/6.0..latest","android-browser/4.2..latest"]},"gitHead":"81532e3600a6284a9cb87ef2f625e89df8f9282a","homepage":"https://github.com/scottcorgan/tiny-emitter","_id":"tiny-emitter@1.0.0","_shasum":"de7473c10cacf92b3a007a4416dd48d8fd0034f9","_from":".","_npmVersion":"1.4.23","_npmUser":{"name":"scottcorgan","email":"scottcorgan@gmail.com"},"maintainers":[{"name":"scottcorgan","email":"scottcorgan@gmail.com"}],"dist":{"shasum":"de7473c10cacf92b3a007a4416dd48d8fd0034f9","tarball":"https://registry.npmjs.org/tiny-emitter/-/tiny-emitter-1.0.0.tgz"},"directories":{}},"1.0.1":{"name":"tiny-emitter","version":"1.0.1","description":"A tiny (less than 1k) event emitter library","main":"index.js","scripts":{"test":"testling | node_modules/.bin/tspec","bundle":"browserify index.js > dist/tinyemitter.js -s TinyEmitter && echo 'Bundled'","minify":"uglifyjs dist/tinyemitter.js -o dist/tinyemitter.min.js -m && echo 'Minified'","build":"npm test && npm run bundle && npm run minify","size":"uglifyjs index.js -o minified.js -m && ls -l && rm minified.js"},"repository":{"type":"git","url":"git+https://github.com/scottcorgan/tiny-emitter.git"},"keywords":["event","emitter","pubsub","tiny","events","bind"],"author":{"name":"Scott Corgan"},"license":"MIT","bugs":{"url":"https://github.com/scottcorgan/tiny-emitter/issues"},"devDependencies":{"browserify":"^11.2.0","tap-spec":"^4.1.0","tape":"^4.2.1","testling":"^1.7.1","uglify-js":"^2.5.0"},"testling":{"files":["test/index.js"],"browsers":["iexplore/10.0","iexplore/9.0","firefox/16..latest","chrome/22..latest","safari/5.1..latest","ipad/6.0..latest","iphone/6.0..latest","android-browser/4.2..latest"]},"gitHead":"bd8c58e4a6c0bcc5bc5c6177e1c572f7433411fc","homepage":"https://github.com/scottcorgan/tiny-emitter#readme","_id":"tiny-emitter@1.0.1","_shasum":"55a5871acd12bee10638f95beb9bafd89830a7c6","_from":".","_npmVersion":"2.14.4","_nodeVersion":"4.1.1","_npmUser":{"name":"scottcorgan","email":"scottcorgan@gmail.com"},"dist":{"shasum":"55a5871acd12bee10638f95beb9bafd89830a7c6","tarball":"https://registry.npmjs.org/tiny-emitter/-/tiny-emitter-1.0.1.tgz"},"maintainers":[{"name":"scottcorgan","email":"scottcorgan@gmail.com"}],"directories":{}},"1.0.2":{"name":"tiny-emitter","version":"1.0.2","description":"A tiny (less than 1k) event emitter library","main":"index.js","scripts":{"test":"testling | tap-format-spec","bundle":"browserify index.js > dist/tinyemitter.js -s TinyEmitter && echo 'Bundled'","minify":"uglifyjs dist/tinyemitter.js -o dist/tinyemitter.min.js -m && echo 'Minified'","build":"npm test && npm run bundle && npm run minify","size":"uglifyjs index.js -o minified.js -m && ls -l && rm minified.js"},"repository":{"type":"git","url":"git+https://github.com/scottcorgan/tiny-emitter.git"},"keywords":["event","emitter","pubsub","tiny","events","bind"],"author":{"name":"Scott Corgan"},"license":"MIT","bugs":{"url":"https://github.com/scottcorgan/tiny-emitter/issues"},"devDependencies":{"@tap-format/spec":"0.2.0","browserify":"^11.2.0","tape":"^4.2.1","testling":"^1.7.1","uglify-js":"^2.5.0"},"testling":{"files":["test/index.js"],"browsers":["iexplore/10.0","iexplore/9.0","firefox/16..latest","chrome/22..latest","safari/5.1..latest","ipad/6.0..latest","iphone/6.0..latest","android-browser/4.2..latest"]},"gitHead":"cc88f1cd3a97258d9f81f44f1fb28f0d3e40fab4","homepage":"https://github.com/scottcorgan/tiny-emitter#readme","_id":"tiny-emitter@1.0.2","_shasum":"8e49470d3f55f89e247210368a6bb9fb51aa1601","_from":".","_npmVersion":"2.14.14","_nodeVersion":"5.1.1","_npmUser":{"name":"scottcorgan","email":"scottcorgan@gmail.com"},"dist":{"shasum":"8e49470d3f55f89e247210368a6bb9fb51aa1601","tarball":"https://registry.npmjs.org/tiny-emitter/-/tiny-emitter-1.0.2.tgz"},"maintainers":[{"name":"scottcorgan","email":"scottcorgan@gmail.com"}],"directories":{}}},"readme":"# tiny-emitter\n \nA tiny (less than 1k) event emitter library. Works in the browser, in Node, and with [Browserify](http://browserify.org).\n\n[![browser support](https://ci.testling.com/scottcorgan/tiny-emitter.png)](https://ci.testling.com/scottcorgan/tiny-emitter)\n \n## Install\n\nNode and Browserify\n\n```\nnpm install tiny-emitter --save\n```\n \nBrowser\n\n```\nbower install tiny-emitter --save\n```\n \n```html\n<script src=\"bower_components/tiny-emitter/dist/tinyemitter.min.js\"></script>\n``` \n\n## Usage\n\nNode and Browserify\n\n```js\nvar Emitter = require('tiny-emitter');\nvar emitter = new Emitter();\n\nemitter.on('some-event', function (arg1, arg2, arg3) {\n //  \n});\n\nemitter.emit('some-event', 'arg1 value', 'arg2 value', 'arg3 value');\n```\n\nBrowser\n\n```js\nvar emitter = new TinyEmitter();\n\nemitter.on('some-event', someCallback);\nemitter.emit('some-event');\n```\n\n## Instance Methods\n\n### on(event, callback[, context])\n\nSubscribe to an event\n\n* `event` - the name of the event to subscribe to\n* `callback` - the function to call when event is emitted\n* `context` - (OPTIONAL) - the context to bind the event callback to\n\n### once(event, callback[, context])\n\nSubscribe to an event only **once**\n\n* `event` - the name of the event to subscribe to\n* `callback` - the function to call when event is emitted\n* `context` - (OPTIONAL) - the context to bind the event callback to\n\n### off(event[, callback])\n\nUnsubscribe from an event or all events. If no callback is provided, it unsubscribes you from all events.\n\n* `event` - the name of the event to unsubscribe from\n* `callback` - the function used when binding to the event\n\n### emit(event[, arguments...])\n\nTrigger a named event\n\n* `event` - the event name to emit\n* `arguments...` - any number of arguments to pass to the event subscribers\n\n## Test and Build\n \nBuild (Tests, Browserifies, and minifies)\n\n```\nnpm install\nnpm run build\n```\n\nTest\n\n```\nnpm install\nnpm test\n```","maintainers":[{"name":"scottcorgan","email":"scottcorgan@gmail.com"}],"time":{"modified":"2015-12-10T19:27:12.356Z","created":"2014-01-03T23:22:38.411Z","0.1.0":"2014-01-03T23:22:38.908Z","0.1.1":"2014-01-04T00:23:57.216Z","0.1.2":"2014-01-04T00:47:19.278Z","0.1.3":"2014-01-04T01:28:13.939Z","0.1.4":"2014-01-04T23:51:25.001Z","0.1.5":"2014-01-05T00:15:42.826Z","0.1.6":"2014-01-06T16:03:14.505Z","0.1.7":"2014-01-06T18:53:41.066Z","0.1.8":"2014-01-09T16:23:49.501Z","0.1.9":"2014-01-09T16:59:31.006Z","0.1.10":"2014-01-09T17:17:05.707Z","0.1.11":"2014-01-09T17:40:27.044Z","0.1.12":"2014-01-23T02:18:53.899Z","1.0.0":"2014-09-16T19:08:32.014Z","1.0.1":"2015-10-14T19:18:30.367Z","1.0.2":"2015-12-10T19:27:12.356Z"},"author":{"name":"Scott Corgan"},"repository":{"type":"git","url":"git+https://github.com/scottcorgan/tiny-emitter.git"},"users":{"parroit":true,"nichoth":true,"jondashkyle":true},"readmeFilename":"README.md","homepage":"https://github.com/scottcorgan/tiny-emitter#readme","keywords":["event","emitter","pubsub","tiny","events","bind"],"bugs":{"url":"https://github.com/scottcorgan/tiny-emitter/issues"},"license":"MIT","_attachments":{},"_etag":"\"DHLXNUVYXZE4L4MC6N6ASPVZ0\""}